jobs_done10/__init__.py
jobs_done10/__main__.py
jobs_done10/_version.py
jobs_done10/cli.py
jobs_done10/common.py
jobs_done10/job_generator.py
jobs_done10/jobs_done_job.py
jobs_done10/repository.py
jobs_done10/server_email_templates.py
jobs_done10/generators/__init__.py
jobs_done10/generators/jenkins.py
jobs_done10/server/__init__.py
jobs_done10/server/app.py
jobs_done10/xml_factory/__init__.py
jobs_done10/xml_factory/_pretty_xml.py
jobs_done10/xml_factory/_xml_factory.py
jobs_done10-1.11.0.dist-info/LICENSE
jobs_done10-1.11.0.dist-info/METADATA
jobs_done10-1.11.0.dist-info/WHEEL
jobs_done10-1.11.0.dist-info/entry_points.txt
jobs_done10-1.11.0.dist-info/top_level.txt
jobs_done10-1.11.0.dist-info/RECORD
