Metadata-Version: 2.1
Name: jobs-done10
Version: 1.11.0
Summary: Job's Done uses a .jobs_done.yaml file in your repository to create Continuous Integration jobs on Jenkins.
Home-page: https://github.com/ESSS/jobs_done10
Author: ESSS
Author-email: dev@esss.com.br
License: MIT
Keywords: jenkins continuous integration ci jobs job build
Classifier: Development Status :: 5 - Production/Stable
Classifier: Intended Audience :: Developers
Classifier: License :: OSI Approved :: MIT License
Classifier: Operating System :: OS Independent
Classifier: Programming Language :: Python :: 3.10
Classifier: Topic :: Software Development
Provides: jobs_done10
Requires-Python: >=3.10
License-File: LICENSE
Requires-Dist: click
Requires-Dist: flask
Requires-Dist: gunicorn
Requires-Dist: pygments
Requires-Dist: python-dotenv
Requires-Dist: python-jenkins
Requires-Dist: pyyaml
Provides-Extra: dev
Requires-Dist: pytest-regressions ; extra == 'dev'
Requires-Dist: pre-commit ; extra == 'dev'
Requires-Dist: pytest-mock ; extra == 'dev'
Requires-Dist: requests-mock ; extra == 'dev'
